[{"benchmark":"dedup.FastCdc2016","mode":"dedup","primaryMetric":{"score":0.98,"scoreUnit":"%","scoreError":0.0,"rawData":[[0.98]]},"secondaryMetrics":{"chunk_count":{"score":311.0,"scoreUnit":"count","scoreError":0.0,"rawData":[[311.0]]},"chunk_size":{"score":2457.67,"scoreUnit":"KB","scoreError":617.95,"rawData":[[1084.49,3584.0]]},"duration":{"score":7.9,"scoreUnit":"second","scoreError":0.0,"rawData":[[7.9]]}}},{"benchmark":"dedup.Pci_64","mode":"dedup","primaryMetric":{"score":0.48,"scoreUnit":"%","scoreError":0.0,"rawData":[[0.48]]},"secondaryMetrics":{"chunk_count":{"score":530.0,"scoreUnit":"count","scoreError":0.0,"rawData":[[530.0]]},"chunk_size":{"score":1442.14,"scoreUnit":"KB","scoreError":754.7,"rawData":[[1024.0,3584.0]]},"duration":{"score":12.37,"scoreUnit":"second","scoreError":0.0,"rawData":[[12.37]]}}},{"benchmark":"dedup.Pci_64_1","mode":"dedup","primaryMetric":{"score":0.48,"scoreUnit":"%","scoreError":0.0,"rawData":[[0.48]]},"secondaryMetrics":{"chunk_count":{"score":525.0,"scoreUnit":"count","scoreError":0.0,"rawData":[[525.0]]},"duration":{"score":11.25,"scoreUnit":"second","scoreError":0.0,"rawData":[[11.25]]},"chunk_size":{"score":1455.88,"scoreUnit":"KB","scoreError":760.48,"rawData":[[1024.0,3584.0]]}}},{"benchmark":"dedup.Pci_64_2","mode":"dedup","primaryMetric":{"score":0.48,"scoreUnit":"%","scoreError":0.0,"rawData":[[0.48]]},"secondaryMetrics":{"chunk_size":{"score":1461.45,"scoreUnit":"KB","scoreError":760.77,"rawData":[[1024.0,3584.0]]},"chunk_count":{"score":523.0,"scoreUnit":"count","scoreError":0.0,"rawData":[[523.0]]},"duration":{"score":12.5,"scoreUnit":"second","scoreError":0.0,"rawData":[[12.5]]}}},{"benchmark":"dedup.Pci_64_3","mode":"dedup","primaryMetric":{"score":0.48,"scoreUnit":"%","scoreError":0.0,"rawData":[[0.48]]},"secondaryMetrics":{"chunk_size":{"score":1475.55,"scoreUnit":"KB","scoreError":765.15,"rawData":[[1024.0,3584.0]]},"chunk_count":{"score":518.0,"scoreUnit":"count","scoreError":0.0,"rawData":[[518.0]]},"duration":{"score":13.58,"scoreUnit":"second","scoreError":0.0,"rawData":[[13.58]]}}},{"benchmark":"dedup.Adler32_simple","mode":"dedup","primaryMetric":{"score":0.0,"scoreUnit":"%","scoreError":0.0,"rawData":[[0.0]]},"secondaryMetrics":{"chunk_count":{"score":305.0,"scoreUnit":"count","scoreError":0.0,"rawData":[[305.0]]},"chunk_size":{"score":2506.02,"scoreUnit":"KB","scoreError":936.91,"rawData":[[1032.72,3584.0]]},"duration":{"score":21.65,"scoreUnit":"second","scoreError":0.0,"rawData":[[21.65]]}}},{"benchmark":"dedup.Adler32_16","mode":"dedup","primaryMetric":{"score":0.0,"scoreUnit":"%","scoreError":0.0,"rawData":[[0.0]]},"secondaryMetrics":{"chunk_count":{"score":215.0,"scoreUnit":"count","scoreError":0.0,"rawData":[[215.0]]},"chunk_size":{"score":3555.05,"scoreUnit":"KB","scoreError":299.7,"rawData":[[3584.0,3584.0]]},"duration":{"score":16.75,"scoreUnit":"second","scoreError":0.0,"rawData":[[16.75]]}}},{"benchmark":"dedup.Adler32_32","mode":"dedup","primaryMetric":{"score":0.0,"scoreUnit":"%","scoreError":0.0,"rawData":[[0.0]]},"secondaryMetrics":{"chunk_size":{"score":3555.05,"scoreUnit":"KB","scoreError":299.7,"rawData":[[3584.0,3584.0]]},"duration":{"score":24.58,"scoreUnit":"second","scoreError":0.0,"rawData":[[24.58]]},"chunk_count":{"score":215.0,"scoreUnit":"count","scoreError":0.0,"rawData":[[215.0]]}}},{"benchmark":"dedup.Adler32_48","mode":"dedup","primaryMetric":{"score":0.0,"scoreUnit":"%","scoreError":0.0,"rawData":[[0.0]]},"secondaryMetrics":{"chunk_size":{"score":3555.05,"scoreUnit":"KB","scoreError":299.7,"rawData":[[3584.0,3584.0]]},"chunk_count":{"score":215.0,"scoreUnit":"count","scoreError":0.0,"rawData":[[215.0]]},"duration":{"score":23.58,"scoreUnit":"second","scoreError":0.0,"rawData":[[23.58]]}}},{"benchmark":"dedup.Adler32_64","mode":"dedup","primaryMetric":{"score":0.0,"scoreUnit":"%","scoreError":0.0,"rawData":[[0.0]]},"secondaryMetrics":{"chunk_size":{"score":3555.05,"scoreUnit":"KB","scoreError":299.7,"rawData":[[3584.0,3584.0]]},"chunk_count":{"score":215.0,"scoreUnit":"count","scoreError":0.0,"rawData":[[215.0]]},"duration":{"score":24.55,"scoreUnit":"second","scoreError":0.0,"rawData":[[24.55]]}}},{"benchmark":"dedup.Adler32_spread","mode":"dedup","primaryMetric":{"score":0.0,"scoreUnit":"%","scoreError":0.0,"rawData":[[0.0]]},"secondaryMetrics":{"duration":{"score":20.9,"scoreUnit":"second","scoreError":0.0,"rawData":[[20.9]]},"chunk_count":{"score":724.0,"scoreUnit":"count","scoreError":0.0,"rawData":[[724.0]]},"chunk_size":{"score":1055.71,"scoreUnit":"KB","scoreError":49.04,"rawData":[[1024.11,1259.22]]}}},{"benchmark":"dedup.Adler32_spread_16","mode":"dedup","primaryMetric":{"score":0.54,"scoreUnit":"%","scoreError":0.0,"rawData":[[0.54]]},"secondaryMetrics":{"chunk_size":{"score":1035.69,"scoreUnit":"KB","scoreError":66.43,"rawData":[[1024.0,1843.77]]},"chunk_count":{"score":738.0,"scoreUnit":"count","scoreError":0.0,"rawData":[[738.0]]},"duration":{"score":15.24,"scoreUnit":"second","scoreError":0.0,"rawData":[[15.24]]}}},{"benchmark":"dedup.Adler32_spread_32","mode":"dedup","primaryMetric":{"score":0.14,"scoreUnit":"%","scoreError":0.0,"rawData":[[0.14]]},"secondaryMetrics":{"chunk_size":{"score":1308.79,"scoreUnit":"KB","scoreError":593.39,"rawData":[[1024.0,3584.0]]},"duration":{"score":17.0,"scoreUnit":"second","scoreError":0.0,"rawData":[[17.0]]},"chunk_count":{"score":584.0,"scoreUnit":"count","scoreError":0.0,"rawData":[[584.0]]}}},{"benchmark":"dedup.Adler32_spread_48","mode":"dedup","primaryMetric":{"score":0.43,"scoreUnit":"%","scoreError":0.0,"rawData":[[0.43]]},"secondaryMetrics":{"chunk_size":{"score":1099.76,"scoreUnit":"KB","scoreError":243.43,"rawData":[[1024.0,3584.0]]},"duration":{"score":16.18,"scoreUnit":"second","scoreError":0.0,"rawData":[[16.18]]},"chunk_count":{"score":695.0,"scoreUnit":"count","scoreError":0.0,"rawData":[[695.0]]}}},{"benchmark":"dedup.Adler32_spread_64","mode":"dedup","primaryMetric":{"score":0.0,"scoreUnit":"%","scoreError":0.0,"rawData":[[0.0]]},"secondaryMetrics":{"chunk_size":{"score":1172.29,"scoreUnit":"KB","scoreError":420.88,"rawData":[[1024.03,3584.0]]},"duration":{"score":14.75,"scoreUnit":"second","scoreError":0.0,"rawData":[[14.75]]},"chunk_count":{"score":652.0,"scoreUnit":"count","scoreError":0.0,"rawData":[[652.0]]}}}]