[{"benchmark":"dedup.FixedSize","mode":"dedup","primaryMetric":{"score":0.0,"scoreUnit":"%","scoreError":0.0,"rawData":[[0.0]]},"secondaryMetrics":{"chunk_count":{"score":188.0,"scoreUnit":"count","scoreError":0.0,"rawData":[[188.0]]},"duration":{"score":14.61,"scoreUnit":"second","scoreError":0.0,"rawData":[[14.61]]},"chunk_size":{"score":4065.62,"scoreUnit":"KB","scoreError":293.0,"rawData":[[4096.0,4096.0]]}}},{"benchmark":"dedup.LeftGear","mode":"dedup","primaryMetric":{"score":0.0,"scoreUnit":"%","scoreError":0.0,"rawData":[[0.0]]},"secondaryMetrics":{"chunk_count":{"score":146.0,"scoreUnit":"count","scoreError":0.0,"rawData":[[146.0]]},"chunk_size":{"score":5235.18,"scoreUnit":"KB","scoreError":1395.65,"rawData":[[2262.58,8192.0]]},"duration":{"score":15.61,"scoreUnit":"second","scoreError":0.0,"rawData":[[15.61]]}}},{"benchmark":"dedup.Ronomon","mode":"dedup","primaryMetric":{"score":0.0,"scoreUnit":"%","scoreError":0.0,"rawData":[[0.0]]},"secondaryMetrics":{"chunk_size":{"score":4522.7,"scoreUnit":"KB","scoreError":2043.66,"rawData":[[2117.67,8192.0]]},"duration":{"score":15.59,"scoreUnit":"second","scoreError":0.0,"rawData":[[15.59]]},"chunk_count":{"score":169.0,"scoreUnit":"count","scoreError":0.0,"rawData":[[169.0]]}}},{"benchmark":"dedup.Ronomon64","mode":"dedup","primaryMetric":{"score":0.42,"scoreUnit":"%","scoreError":0.0,"rawData":[[0.42]]},"secondaryMetrics":{"chunk_count":{"score":170.0,"scoreUnit":"count","scoreError":0.0,"rawData":[[170.0]]},"chunk_size":{"score":4496.09,"scoreUnit":"KB","scoreError":2092.96,"rawData":[[2069.15,8192.0]]},"duration":{"score":14.04,"scoreUnit":"second","scoreError":0.0,"rawData":[[14.04]]}}},{"benchmark":"dedup.Buzhash32_64","mode":"dedup","primaryMetric":{"score":0.0,"scoreUnit":"%","scoreError":0.0,"rawData":[[0.0]]},"secondaryMetrics":{"chunk_size":{"score":2359.06,"scoreUnit":"KB","scoreError":661.31,"rawData":[[2048.0,7038.59]]},"chunk_count":{"score":324.0,"scoreUnit":"count","scoreError":0.0,"rawData":[[324.0]]},"duration":{"score":15.65,"scoreUnit":"second","scoreError":0.0,"rawData":[[15.65]]}}},{"benchmark":"dedup.Buzhash32Reg_64","mode":"dedup","primaryMetric":{"score":0.0,"scoreUnit":"%","scoreError":0.0,"rawData":[[0.0]]},"secondaryMetrics":{"chunk_size":{"score":2316.17,"scoreUnit":"KB","scoreError":474.07,"rawData":[[2048.0,5432.38]]},"duration":{"score":16.48,"scoreUnit":"second","scoreError":0.0,"rawData":[[16.48]]},"chunk_count":{"score":330.0,"scoreUnit":"count","scoreError":0.0,"rawData":[[330.0]]}}},{"benchmark":"dedup.Buzhash64_48","mode":"dedup","primaryMetric":{"score":0.0,"scoreUnit":"%","scoreError":0.0,"rawData":[[0.0]]},"secondaryMetrics":{"chunk_count":{"score":139.0,"scoreUnit":"count","scoreError":0.0,"rawData":[[139.0]]},"chunk_size":{"score":5498.82,"scoreUnit":"KB","scoreError":2274.23,"rawData":[[2054.18,8192.0]]},"duration":{"score":16.44,"scoreUnit":"second","scoreError":0.0,"rawData":[[16.44]]}}},{"benchmark":"dedup.Buzhash64_64","mode":"dedup","primaryMetric":{"score":0.0,"scoreUnit":"%","scoreError":0.0,"rawData":[[0.0]]},"secondaryMetrics":{"chunk_count":{"score":270.0,"scoreUnit":"count","scoreError":0.0,"rawData":[[270.0]]},"chunk_size":{"score":2830.87,"scoreUnit":"KB","scoreError":1316.71,"rawData":[[2048.0,8192.0]]},"duration":{"score":15.96,"scoreUnit":"second","scoreError":0.0,"rawData":[[15.96]]}}},{"benchmark":"dedup.Buzhash64_256","mode":"dedup","primaryMetric":{"score":0.0,"scoreUnit":"%","scoreError":0.0,"rawData":[[0.0]]},"secondaryMetrics":{"duration":{"score":15.34,"scoreUnit":"second","scoreError":0.0,"rawData":[[15.34]]},"chunk_size":{"score":2681.88,"scoreUnit":"KB","scoreError":1021.65,"rawData":[[2048.0,8192.0]]},"chunk_count":{"score":285.0,"scoreUnit":"count","scoreError":0.0,"rawData":[[285.0]]}}},{"benchmark":"dedup.Buzhash64Reg_48","mode":"dedup","primaryMetric":{"score":0.41,"scoreUnit":"%","scoreError":0.0,"rawData":[[0.41]]},"secondaryMetrics":{"chunk_count":{"score":187.0,"scoreUnit":"count","scoreError":0.0,"rawData":[[187.0]]},"chunk_size":{"score":4087.36,"scoreUnit":"KB","scoreError":1775.47,"rawData":[[2074.33,8164.45]]},"duration":{"score":16.33,"scoreUnit":"second","scoreError":0.0,"rawData":[[16.33]]}}},{"benchmark":"dedup.Buzhash64Reg_64","mode":"dedup","primaryMetric":{"score":0.0,"scoreUnit":"%","scoreError":0.0,"rawData":[[0.0]]},"secondaryMetrics":{"chunk_count":{"score":287.0,"scoreUnit":"count","scoreError":0.0,"rawData":[[287.0]]},"duration":{"score":15.58,"scoreUnit":"second","scoreError":0.0,"rawData":[[15.58]]},"chunk_size":{"score":2663.19,"scoreUnit":"KB","scoreError":982.14,"rawData":[[2048.0,7123.65]]}}},{"benchmark":"dedup.Buzhash64Reg_256","mode":"dedup","primaryMetric":{"score":0.0,"scoreUnit":"%","scoreError":0.0,"rawData":[[0.0]]},"secondaryMetrics":{"chunk_size":{"score":2653.94,"scoreUnit":"KB","scoreError":882.52,"rawData":[[2048.0,7899.13]]},"chunk_count":{"score":288.0,"scoreUnit":"count","scoreError":0.0,"rawData":[[288.0]]},"duration":{"score":15.46,"scoreUnit":"second","scoreError":0.0,"rawData":[[15.46]]}}},{"benchmark":"dedup.FastCdc2016","mode":"dedup","primaryMetric":{"score":0.0,"scoreUnit":"%","scoreError":0.0,"rawData":[[0.0]]},"secondaryMetrics":{"chunk_size":{"score":4963.22,"scoreUnit":"KB","scoreError":1340.18,"rawData":[[2276.22,8192.0]]},"chunk_count":{"score":154.0,"scoreUnit":"count","scoreError":0.0,"rawData":[[154.0]]},"duration":{"score":15.98,"scoreUnit":"second","scoreError":0.0,"rawData":[[15.98]]}}},{"benchmark":"dedup.FastCdc2020","mode":"dedup","primaryMetric":{"score":0.0,"scoreUnit":"%","scoreError":0.0,"rawData":[[0.0]]},"secondaryMetrics":{"chunk_count":{"score":158.0,"scoreUnit":"count","scoreError":0.0,"rawData":[[158.0]]},"duration":{"score":15.91,"scoreUnit":"second","scoreError":0.0,"rawData":[[15.91]]},"chunk_size":{"score":4837.57,"scoreUnit":"KB","scoreError":1223.27,"rawData":[[1189.33,8010.26]]}}},{"benchmark":"dedup.Restic","mode":"dedup","primaryMetric":{"score":0.0,"scoreUnit":"%","scoreError":0.0,"rawData":[[0.0]]},"secondaryMetrics":{"chunk_count":{"score":262.0,"scoreUnit":"count","scoreError":0.0,"rawData":[[262.0]]},"duration":{"score":15.95,"scoreUnit":"second","scoreError":0.0,"rawData":[[15.95]]},"chunk_size":{"score":2917.31,"scoreUnit":"KB","scoreError":1438.81,"rawData":[[2048.0,8192.0]]}}},{"benchmark":"dedup.StadiaCdc","mode":"dedup","primaryMetric":{"score":0.0,"scoreUnit":"%","scoreError":0.0,"rawData":[[0.0]]},"secondaryMetrics":{"chunk_size":{"score":3899.67,"scoreUnit":"KB","scoreError":1642.3,"rawData":[[2055.53,8100.77]]},"duration":{"score":15.15,"scoreUnit":"second","scoreError":0.0,"rawData":[[15.15]]},"chunk_count":{"score":196.0,"scoreUnit":"count","scoreError":0.0,"rawData":[[196.0]]}}},{"benchmark":"dedup.Casync","mode":"dedup","primaryMetric":{"score":0.0,"scoreUnit":"%","scoreError":0.0,"rawData":[[0.0]]},"secondaryMetrics":{"duration":{"score":19.95,"scoreUnit":"second","scoreError":0.0,"rawData":[[19.95]]},"chunk_count":{"score":133.0,"scoreUnit":"count","scoreError":0.0,"rawData":[[133.0]]},"chunk_size":{"score":5746.89,"scoreUnit":"KB","scoreError":2201.05,"rawData":[[2103.96,8192.0]]}}}]