[{"benchmark":"dedup.FastCdc2016","mode":"dedup","primaryMetric":{"score":0.85,"scoreUnit":"%","scoreError":0.0,"rawData":[[0.85]]},"secondaryMetrics":{"chunk_size":{"score":1152.84,"scoreUnit":"KB","scoreError":168.36,"rawData":[[533.7,1280.0]]},"chunk_count":{"score":663.0,"scoreUnit":"count","scoreError":0.0,"rawData":[[663.0]]},"duration":{"score":13.14,"scoreUnit":"second","scoreError":0.0,"rawData":[[13.14]]}}},{"benchmark":"dedup.Pci_64","mode":"dedup","primaryMetric":{"score":0.38,"scoreUnit":"%","scoreError":0.0,"rawData":[[0.38]]},"secondaryMetrics":{"duration":{"score":14.17,"scoreUnit":"second","scoreError":0.0,"rawData":[[14.17]]},"chunk_count":{"score":1054.0,"scoreUnit":"count","scoreError":0.0,"rawData":[[1054.0]]},"chunk_size":{"score":725.18,"scoreUnit":"KB","scoreError":292.49,"rawData":[[512.0,1280.0]]}}},{"benchmark":"dedup.Pci_128","mode":"dedup","primaryMetric":{"score":0.62,"scoreUnit":"%","scoreError":0.0,"rawData":[[0.62]]},"secondaryMetrics":{"duration":{"score":19.37,"scoreUnit":"second","scoreError":0.0,"rawData":[[19.37]]},"chunk_count":{"score":1020.0,"scoreUnit":"count","scoreError":0.0,"rawData":[[1020.0]]},"chunk_size":{"score":749.35,"scoreUnit":"KB","scoreError":295.96,"rawData":[[512.0,1280.0]]}}},{"benchmark":"dedup.Pci_256","mode":"dedup","primaryMetric":{"score":1.14,"scoreUnit":"%","scoreError":0.0,"rawData":[[1.14]]},"secondaryMetrics":{"duration":{"score":16.27,"scoreUnit":"second","scoreError":0.0,"rawData":[[16.27]]},"chunk_count":{"score":977.0,"scoreUnit":"count","scoreError":0.0,"rawData":[[977.0]]},"chunk_size":{"score":782.33,"scoreUnit":"KB","scoreError":304.85,"rawData":[[512.0,1280.0]]}}},{"benchmark":"dedup.Pci_512","mode":"dedup","primaryMetric":{"score":0.4,"scoreUnit":"%","scoreError":0.0,"rawData":[[0.4]]},"secondaryMetrics":{"chunk_count":{"score":930.0,"scoreUnit":"count","scoreError":0.0,"rawData":[[930.0]]},"duration":{"score":15.77,"scoreUnit":"second","scoreError":0.0,"rawData":[[15.77]]},"chunk_size":{"score":821.87,"scoreUnit":"KB","scoreError":315.41,"rawData":[[512.0,1280.0]]}}}]